<annotation>
  <folder>Gears</folder>
  <filename>VID_20170206_165500_30.jpg</filename>
  <path>C:\Users\Robotics\Pictures\Gears\VID_20170206_165500 30.jpg</path>
  <source>
    <database>Unknown</database>
  </source>
  <size>
    <width>640</width>
    <height>360</height>
    <depth>3</depth>
  </size>
  <segmented>0</segmented>
  <object>
    <name>gear</name>
    <pose>Unspecified</pose>
    <truncated>0</truncated>
    <difficult>0</difficult>
    <bndbox>
      <xmin>288</xmin>
      <ymin>116</ymin>
      <xmax>517</xmax>
      <ymax>321</ymax>
    </bndbox>
  </object>
</annotation>
