<annotation>
  <folder>batch1</folder>
  <filename>GEAR_BATCH_3_31</filename>
  <path>C:\Users\Programming\Documents\batch1\GEAR_BATCH_3_31.jpg</path>
  <source>
    <database>Unknown</database>
  </source>
  <size>
    <width>768</width>
    <height>432</height>
    <depth>3</depth>
  </size>
  <segmented>0</segmented>
  <object>
    <name>gear</name>
    <pose>Unspecified</pose>
    <truncated>0</truncated>
    <difficult>0</difficult>
    <bndbox>
      <xmin>238</xmin>
      <ymin>111</ymin>
      <xmax>367</xmax>
      <ymax>227</ymax>
    </bndbox>
  </object>
  <object>
    <name>gear</name>
    <pose>Unspecified</pose>
    <truncated>0</truncated>
    <difficult>0</difficult>
    <bndbox>
      <xmin>344</xmin>
      <ymin>261</ymin>
      <xmax>488</xmax>
      <ymax>404</ymax>
    </bndbox>
  </object>
</annotation>
