<annotation>
  <folder>batch1</folder>
  <filename>GEAR_BATCH_3_13</filename>
  <path>C:\Users\Programming\Documents\batch1\GEAR_BATCH_3_13.jpg</path>
  <source>
    <database>Unknown</database>
  </source>
  <size>
    <width>768</width>
    <height>432</height>
    <depth>3</depth>
  </size>
  <segmented>0</segmented>
  <object>
    <name>gear</name>
    <pose>Unspecified</pose>
    <truncated>0</truncated>
    <difficult>0</difficult>
    <bndbox>
      <xmin>112</xmin>
      <ymin>194</ymin>
      <xmax>251</xmax>
      <ymax>324</ymax>
    </bndbox>
  </object>
  <object>
    <name>gear</name>
    <pose>Unspecified</pose>
    <truncated>0</truncated>
    <difficult>0</difficult>
    <bndbox>
      <xmin>324</xmin>
      <ymin>136</ymin>
      <xmax>462</xmax>
      <ymax>263</ymax>
    </bndbox>
  </object>
</annotation>
